strategy_field/__init__.py
strategy_field/admin.py
strategy_field/config.py
strategy_field/exceptions.py
strategy_field/fields.py
strategy_field/forms.py
strategy_field/registry.py
strategy_field/utils.py
strategy_field/validators.py
strategy_field/version.py
strategy_field/contrib/__init__.py
strategy_field/contrib/drf.py
django_strategy_field-3.2.1.dist-info/METADATA
django_strategy_field-3.2.1.dist-info/WHEEL
django_strategy_field-3.2.1.dist-info/licenses/LICENSE
django_strategy_field-3.2.1.dist-info/RECORD
